blanc/__init__.py
blanc/__main__.py
blanc/__version__.py
blanc/blanc.py
blanc/estime.py
blanc/shannon.py
blanc/utils.py
blanc/version.json
blanc-0.3.4.dist-info/LICENSE
blanc-0.3.4.dist-info/METADATA
blanc-0.3.4.dist-info/WHEEL
blanc-0.3.4.dist-info/entry_points.txt
blanc-0.3.4.dist-info/top_level.txt
blanc-0.3.4.dist-info/RECORD
