Metadata-Version: 2.1
Name: blanc
Version: 0.3.4
Summary: Human-free quality estimation of document summaries
Home-page: https://github.com/PrimerAI/blanc
Author: Primer AI
Author-email: blanc@primer.ai
Classifier: Programming Language :: Python :: 3
Classifier: License :: OSI Approved :: MIT License
Classifier: Operating System :: OS Independent
Requires-Python: >=3.6
License-File: LICENSE
Requires-Dist: nltk (<4.0,>=3.1)
Requires-Dist: numpy (<2.0,>=1.0)
Requires-Dist: scipy (>=1.6.0)
Requires-Dist: torch (<2.0,>=1.0)
Requires-Dist: tqdm (<5.0,>=4.27.0)
Requires-Dist: transformers (>=2.4.0)
